lightweaver-0.16.1.dist-info/RECORD
lightweaver-0.16.1.dist-info/WHEEL
lightweaver-0.16.1.dist-info/top_level.txt
lightweaver-0.16.1.dist-info/METADATA
lightweaver-0.16.1.dist-info/licenses/LICENSE
lightweaver/zeeman.py
lightweaver/nr_update.py
lightweaver/libenkiTS.so
lightweaver/barklem.py
lightweaver/atomic_table.py
lightweaver/atomic_set.py
lightweaver/config.py
lightweaver/version.py
lightweaver/benchmark.py
lightweaver/molecule.py
lightweaver/crtaf.py
lightweaver/simd_management.py
lightweaver/atomic_model.py
lightweaver/rh_atoms.py
lightweaver/wittmann.py
lightweaver/constants.py
lightweaver/multi.py
lightweaver/__init__.py
lightweaver/collisional_rates.py
lightweaver/utils.py
lightweaver/iterate_ctx.py
lightweaver/broadening.py
lightweaver/iteration_update.py
lightweaver/atmosphere.py
lightweaver/fal.py
lightweaver/LwCompiled.cpython-313-darwin.so
lightweaver/DefaultIterSchemes/.placeholder
lightweaver/DefaultIterSchemes/SimdImpl_SSE2.cpython-313-darwin.so
lightweaver/DefaultIterSchemes/SimdImpl_AVX512.cpython-313-darwin.so
lightweaver/DefaultIterSchemes/SimdImpl_AVX2FMA.cpython-313-darwin.so
lightweaver/Data/Quadratures.pickle
lightweaver/Data/Barklem_spdata.dat
lightweaver/Data/AtomicMassesNames.pickle
lightweaver/Data/Barklem_pddata.dat
lightweaver/Data/pf_Kurucz.input
lightweaver/Data/Barklem_dfdata.dat
lightweaver/Data/AbundancesAsplund09.pickle
lightweaver/Data/DefaultMolecules/CH.molecule
lightweaver/Data/DefaultMolecules/LiH.molecule
lightweaver/Data/DefaultMolecules/NH.molecule
lightweaver/Data/DefaultMolecules/CN.molecule
lightweaver/Data/DefaultMolecules/CO.molecule
lightweaver/Data/DefaultMolecules/H2+.molecule
lightweaver/Data/DefaultMolecules/MgH.molecule
lightweaver/Data/DefaultMolecules/NO.molecule
lightweaver/Data/DefaultMolecules/OH.molecule
lightweaver/Data/DefaultMolecules/CaH.molecule
lightweaver/Data/DefaultMolecules/TiO.molecule
lightweaver/Data/DefaultMolecules/O2.molecule
lightweaver/Data/DefaultMolecules/H2O.molecule
lightweaver/Data/DefaultMolecules/HF.molecule
lightweaver/Data/DefaultMolecules/CO_NLTE.molecule
lightweaver/Data/DefaultMolecules/H2.molecule
