Metadata-Version: 2.4
Name: lightweaver
Version: 0.16.1
Summary: Non-LTE Radiative Transfer Framework in Python
Author-email: Chris Osborne <lw@contextuallight.com>
Maintainer-email: Chris Osborne <lw@contextuallight.com>
License-Expression: MIT
Requires-Python: >=3.10
License-File: LICENSE
Requires-Dist: numpy>=2.0
Requires-Dist: numba~=0.60
Requires-Dist: matplotlib
Requires-Dist: scipy
Requires-Dist: parse
Requires-Dist: specutils
Requires-Dist: tqdm
Requires-Dist: weno4
Requires-Dist: pyyaml
Requires-Dist: mda-xdrlib; python_version > "3.12"
Dynamic: license-file
